{"2024-03-11-2024-03-11": {"VEN - Nicolás Maduro - TW": [{"valor": 1369, "palabra": "maduro"}, {"valor": 1341, "palabra": "presidente"}, {"valor": 1221, "palabra": "nuestro"}, {"valor": 876, "palabra": "venezuela"}, {"valor": 772, "palabra": "pueblo"}, {"valor": 648, "palabra": "nuestra"}, {"valor": 647, "palabra": "nicolás"}, {"valor": 501, "palabra": "patria"}, {"valor": 432, "palabra": "ambiente"}, {"valor": 414, "palabra": "programa"}, {"valor": 399, "palabra": "siempre"}, {"valor": 395, "palabra": "venceremos"}, {"valor": 367, "palabra": "nuestros"}, {"valor": 350, "palabra": "ilegal"}, {"valor": 339, "palabra": "candidato"}, {"valor": 338, "palabra": "seguimos"}, {"valor": 337, "palabra": "minería"}, {"valor": 336, "palabra": "estado"}, {"valor": 307, "palabra": "parques"}, {"valor": 300, "palabra": "protección"}, {"valor": 249, "palabra": "nacional"}, {"valor": 225, "palabra": "gobierno"}, {"valor": 225, "palabra": "porque"}, {"valor": 218, "palabra": "territorio"}, {"valor": 217, "palabra": "contra"}, {"valor": 209, "palabra": "elecciones"}, {"valor": 208, "palabra": "nacionales"}, {"valor": 200, "palabra": "cumpliendo"}, {"valor": 199, "palabra": "venezolano"}, {"valor": 186, "palabra": "bienestar"}, {"valor": 185, "palabra": "cuando"}, {"valor": 184, "palabra": "naturales"}, {"valor": 183, "palabra": "compromiso"}, {"valor": 182, "palabra": "venezolanos"}, {"valor": 182, "palabra": "naturaleza"}, {"valor": 177, "palabra": "comandante"}, {"valor": 172, "palabra": "sintonía"}, {"valor": 161, "palabra": "lealtad"}, {"valor": 160, "palabra": "municipio"}, {"valor": 153, "palabra": "victoria"}]}, "2024-03-12-2024-03-12": {"VEN - Nicolás Maduro - TW": [{"valor": 1146, "palabra": "nuestro"}, {"valor": 956, "palabra": "presidente"}, {"valor": 927, "palabra": "maduro"}, {"valor": 757, "palabra": "venezuela"}, {"valor": 689, "palabra": "pueblo"}, {"valor": 644, "palabra": "nuestra"}, {"valor": 634, "palabra": "ambiente"}, {"valor": 551, "palabra": "ilegal"}, {"valor": 529, "palabra": "minería"}, {"valor": 507, "palabra": "nicolás"}, {"valor": 443, "palabra": "nuestros"}, {"valor": 397, "palabra": "protección"}, {"valor": 393, "palabra": "siempre"}, {"valor": 350, "palabra": "patria"}, {"valor": 333, "palabra": "contra"}, {"valor": 302, "palabra": "nacional"}, {"valor": 286, "palabra": "venceremos"}, {"valor": 282, "palabra": "ambiental"}, {"valor": 276, "palabra": "territorio"}, {"valor": 258, "palabra": "venezolano"}, {"valor": 219, "palabra": "parques"}, {"valor": 204, "palabra": "seguimos"}, {"valor": 193, "palabra": "naturales"}, {"valor": 184, "palabra": "ilegales"}, {"valor": 180, "palabra": "nacionales"}, {"valor": 175, "palabra": "defensa"}, {"valor": 174, "palabra": "gobierno"}, {"valor": 171, "palabra": "porque"}, {"valor": 170, "palabra": "proteger"}, {"valor": 169, "palabra": "derecho"}, {"valor": 161, "palabra": "mineros"}, {"valor": 157, "palabra": "cuando"}, {"valor": 156, "palabra": "gracias"}, {"valor": 149, "palabra": "venezolanos"}, {"valor": 143, "palabra": "estado"}, {"valor": 141, "palabra": "recursos"}, {"valor": 141, "palabra": "trabajando"}, {"valor": 138, "palabra": "candidato"}, {"valor": 136, "palabra": "compromiso"}, {"valor": 135, "palabra": "trabajo"}]}, "2024-03-13-2024-03-13": {"VEN - Nicolás Maduro - TW": [{"valor": 904, "palabra": "presidente"}, {"valor": 882, "palabra": "venezuela"}, {"valor": 817, "palabra": "maduro"}, {"valor": 729, "palabra": "nuestro"}, {"valor": 533, "palabra": "pueblo"}, {"valor": 476, "palabra": "ambiente"}, {"valor": 473, "palabra": "nuestra"}, {"valor": 460, "palabra": "nicolás"}, {"valor": 416, "palabra": "ilegal"}, {"valor": 400, "palabra": "minería"}, {"valor": 319, "palabra": "contra"}, {"valor": 273, "palabra": "siempre"}, {"valor": 260, "palabra": "gobierno"}, {"valor": 258, "palabra": "venceremos"}, {"valor": 244, "palabra": "nuestros"}, {"valor": 244, "palabra": "protección"}, {"valor": 238, "palabra": "patria"}, {"valor": 222, "palabra": "trabajando"}, {"valor": 210, "palabra": "porque"}, {"valor": 199, "palabra": "estado"}, {"valor": 175, "palabra": "trabajo"}, {"valor": 163, "palabra": "nacional"}, {"valor": 162, "palabra": "seguimos"}, {"valor": 160, "palabra": "cuando"}, {"valor": 146, "palabra": "gracias"}, {"valor": 140, "palabra": "territorio"}, {"valor": 139, "palabra": "venezolano"}, {"valor": 137, "palabra": "venezolanos"}, {"valor": 124, "palabra": "preservar"}, {"valor": 123, "palabra": "ambiental"}, {"valor": 119, "palabra": "defensa"}, {"valor": 119, "palabra": "nacionales"}, {"valor": 110, "palabra": "parques"}, {"valor": 108, "palabra": "victoria"}, {"valor": 103, "palabra": "ustedes"}, {"valor": 101, "palabra": "juntos"}, {"valor": 100, "palabra": "nosotros"}, {"valor": 99, "palabra": "proteger"}, {"valor": 96, "palabra": "derecho"}, {"valor": 94, "palabra": "tienen"}]}, "2024-03-14-2024-03-14": {"VEN - Nicolás Maduro - TW": [{"valor": 2279, "palabra": "nuestro"}, {"valor": 1967, "palabra": "ambiente"}, {"valor": 1286, "palabra": "presidente"}, {"valor": 1213, "palabra": "nuestra"}, {"valor": 1210, "palabra": "venezuela"}, {"valor": 1152, "palabra": "maduro"}, {"valor": 955, "palabra": "pueblo"}, {"valor": 841, "palabra": "patria"}, {"valor": 735, "palabra": "siempre"}, {"valor": 690, "palabra": "ilegal"}, {"valor": 679, "palabra": "territorio"}, {"valor": 666, "palabra": "venceremos"}, {"valor": 628, "palabra": "nuestros"}, {"valor": 619, "palabra": "proteger"}, {"valor": 613, "palabra": "minería"}, {"valor": 572, "palabra": "defensa"}, {"valor": 558, "palabra": "nicolás"}, {"valor": 484, "palabra": "nacionales"}, {"valor": 482, "palabra": "seguridad"}, {"valor": 482, "palabra": "protección"}, {"valor": 446, "palabra": "contra"}, {"valor": 427, "palabra": "parques"}, {"valor": 408, "palabra": "seguimos"}, {"valor": 402, "palabra": "naturales"}, {"valor": 380, "palabra": "nacional"}, {"valor": 367, "palabra": "planeta"}, {"valor": 357, "palabra": "venezolano"}, {"valor": 322, "palabra": "derecho"}, {"valor": 320, "palabra": "trabajo"}, {"valor": 318, "palabra": "cumplimiento"}, {"valor": 318, "palabra": "preservación"}, {"valor": 315, "palabra": "resguardo"}, {"valor": 304, "palabra": "estado"}, {"valor": 295, "palabra": "ambiental"}, {"valor": 292, "palabra": "gobierno"}, {"valor": 290, "palabra": "porque"}, {"valor": 282, "palabra": "reservas"}, {"valor": 257, "palabra": "futuro"}, {"valor": 254, "palabra": "bolívar"}, {"valor": 250, "palabra": "excelente"}]}, "2024-03-15-2024-03-15": {"VEN - Nicolás Maduro - TW": [{"valor": 943, "palabra": "presidente"}, {"valor": 851, "palabra": "maduro"}, {"valor": 675, "palabra": "venezuela"}, {"valor": 617, "palabra": "pueblo"}, {"valor": 548, "palabra": "nuestro"}, {"valor": 423, "palabra": "nicolás"}, {"valor": 298, "palabra": "nuestra"}, {"valor": 283, "palabra": "patria"}, {"valor": 254, "palabra": "ambiente"}, {"valor": 226, "palabra": "gobierno"}, {"valor": 198, "palabra": "porque"}, {"valor": 192, "palabra": "nuestros"}, {"valor": 191, "palabra": "venceremos"}, {"valor": 173, "palabra": "chávez"}, {"valor": 173, "palabra": "siempre"}, {"valor": 167, "palabra": "venezolano"}, {"valor": 152, "palabra": "estado"}, {"valor": 148, "palabra": "cuando"}, {"valor": 140, "palabra": "gracias"}, {"valor": 130, "palabra": "contra"}, {"valor": 118, "palabra": "seguimos"}, {"valor": 113, "palabra": "venezolanos"}, {"valor": 107, "palabra": "sector"}, {"valor": 105, "palabra": "nicolas"}, {"valor": 104, "palabra": "tienen"}, {"valor": 103, "palabra": "defensa"}, {"valor": 102, "palabra": "municipio"}, {"valor": 100, "palabra": "nacional"}, {"valor": 98, "palabra": "ustedes"}, {"valor": 93, "palabra": "ilegal"}, {"valor": 93, "palabra": "futuro"}, {"valor": 93, "palabra": "excelente"}, {"valor": 92, "palabra": "elecciones"}, {"valor": 91, "palabra": "seguridad"}, {"valor": 90, "palabra": "verdad"}, {"valor": 89, "palabra": "recursos"}, {"valor": 88, "palabra": "carúpano"}, {"valor": 85, "palabra": "guerra"}, {"valor": 84, "palabra": "compromiso"}, {"valor": 83, "palabra": "tenemos"}]}, "2024-03-16-2024-03-16": {"VEN - Nicolás Maduro - TW": [{"valor": 1132, "palabra": "maduro"}, {"valor": 911, "palabra": "presidente"}, {"valor": 848, "palabra": "pueblo"}, {"valor": 768, "palabra": "venezuela"}, {"valor": 659, "palabra": "nicolás"}, {"valor": 549, "palabra": "nuestro"}, {"valor": 517, "palabra": "venceremos"}, {"valor": 384, "palabra": "candidato"}, {"valor": 300, "palabra": "nuestra"}, {"valor": 260, "palabra": "patria"}, {"valor": 238, "palabra": "porque"}, {"valor": 237, "palabra": "siempre"}, {"valor": 215, "palabra": "elecciones"}, {"valor": 183, "palabra": "chávez"}, {"valor": 171, "palabra": "gobierno"}, {"valor": 164, "palabra": "contra"}, {"valor": 162, "palabra": "victoria"}, {"valor": 160, "palabra": "tienen"}, {"valor": 157, "palabra": "cuando"}, {"valor": 155, "palabra": "nacional"}, {"valor": 154, "palabra": "venezolano"}, {"valor": 144, "palabra": "ambiente"}, {"valor": 141, "palabra": "seguimos"}, {"valor": 125, "palabra": "venezolanos"}, {"valor": 120, "palabra": "gracias"}, {"valor": 120, "palabra": "nicolas"}, {"valor": 119, "palabra": "presidencial"}, {"valor": 116, "palabra": "ustedes"}, {"valor": 112, "palabra": "nosotros"}, {"valor": 112, "palabra": "estado"}, {"valor": 111, "palabra": "también"}, {"valor": 111, "palabra": "estamos"}, {"valor": 109, "palabra": "ilegal"}, {"valor": 108, "palabra": "presidenciales"}, {"valor": 100, "palabra": "venciendo"}, {"valor": 100, "palabra": "primero"}, {"valor": 99, "palabra": "minería"}, {"valor": 97, "palabra": "candidatura"}, {"valor": 97, "palabra": "quiere"}, {"valor": 96, "palabra": "poliedro"}]}, "2024-03-17-2024-03-17": {"VEN - Nicolás Maduro - TW": [{"valor": 1484, "palabra": "maduro"}, {"valor": 1186, "palabra": "presidente"}, {"valor": 1020, "palabra": "venezuela"}, {"valor": 960, "palabra": "pueblo"}, {"valor": 806, "palabra": "nicolás"}, {"valor": 671, "palabra": "nuestro"}, {"valor": 459, "palabra": "patria"}, {"valor": 349, "palabra": "porque"}, {"valor": 318, "palabra": "nuestra"}, {"valor": 306, "palabra": "candidato"}, {"valor": 293, "palabra": "gobierno"}, {"valor": 293, "palabra": "siempre"}, {"valor": 288, "palabra": "cuando"}, {"valor": 269, "palabra": "chávez"}, {"valor": 266, "palabra": "elecciones"}, {"valor": 248, "palabra": "venceremos"}, {"valor": 238, "palabra": "ambiente"}, {"valor": 216, "palabra": "garcía"}, {"valor": 211, "palabra": "contra"}, {"valor": 209, "palabra": "venezolano"}, {"valor": 204, "palabra": "tienen"}, {"valor": 185, "palabra": "defensa"}, {"valor": 175, "palabra": "estado"}, {"valor": 174, "palabra": "nicolas"}, {"valor": 168, "palabra": "nacional"}, {"valor": 167, "palabra": "primero"}, {"valor": 164, "palabra": "venezolanos"}, {"valor": 157, "palabra": "bolivariana"}, {"valor": 150, "palabra": "quiere"}, {"valor": 150, "palabra": "jajajaja"}, {"valor": 144, "palabra": "victoria"}, {"valor": 144, "palabra": "ustedes"}, {"valor": 144, "palabra": "seguimos"}, {"valor": 139, "palabra": "economía"}, {"valor": 138, "palabra": "corina"}, {"valor": 129, "palabra": "cerrado"}, {"valor": 128, "palabra": "hambre"}, {"valor": 128, "palabra": "leocenis"}, {"valor": 127, "palabra": "escenario"}, {"valor": 124, "palabra": "sacaría"}]}, "2024-03-18-2024-03-18": {"VEN - Nicolás Maduro - TW": [{"valor": 1728, "palabra": "presidente"}, {"valor": 1443, "palabra": "maduro"}, {"valor": 1117, "palabra": "venezuela"}, {"valor": 918, "palabra": "pueblo"}, {"valor": 687, "palabra": "nicolás"}, {"valor": 651, "palabra": "nuestro"}, {"valor": 457, "palabra": "patria"}, {"valor": 447, "palabra": "estado"}, {"valor": 406, "palabra": "siempre"}, {"valor": 369, "palabra": "nuestra"}, {"valor": 296, "palabra": "porque"}, {"valor": 283, "palabra": "gobierno"}, {"valor": 280, "palabra": "venceremos"}, {"valor": 273, "palabra": "cumaná"}, {"valor": 239, "palabra": "cuando"}, {"valor": 224, "palabra": "chávez"}, {"valor": 220, "palabra": "elecciones"}, {"valor": 214, "palabra": "sector"}, {"valor": 211, "palabra": "municipio"}, {"valor": 204, "palabra": "nuestros"}, {"valor": 198, "palabra": "victoria"}, {"valor": 195, "palabra": "candidato"}, {"valor": 182, "palabra": "cumplimiento"}, {"valor": 174, "palabra": "programa"}, {"valor": 170, "palabra": "nacional"}, {"valor": 164, "palabra": "gracias"}, {"valor": 162, "palabra": "social"}, {"valor": 160, "palabra": "venezolano"}, {"valor": 159, "palabra": "tienen"}, {"valor": 150, "palabra": "venezolanos"}, {"valor": 144, "palabra": "contra"}, {"valor": 143, "palabra": "nicolas"}, {"valor": 141, "palabra": "quiere"}, {"valor": 139, "palabra": "corina"}, {"valor": 138, "palabra": "seguimos"}, {"valor": 136, "palabra": "ustedes"}, {"valor": 135, "palabra": "república"}, {"valor": 135, "palabra": "entregaron"}, {"valor": 131, "palabra": "buenas"}, {"valor": 131, "palabra": "través"}]}}