{"2024-03-04-2024-03-04": {"VEN - Nicolás Maduro - TW": [{"valor": 1238, "palabra": "presidente"}, {"valor": 1132, "palabra": "maduro"}, {"valor": 850, "palabra": "venezuela"}, {"valor": 669, "palabra": "pueblo"}, {"valor": 622, "palabra": "nuestro"}, {"valor": 515, "palabra": "nicolás"}, {"valor": 289, "palabra": "patria"}, {"valor": 267, "palabra": "gobierno"}, {"valor": 264, "palabra": "nuestra"}, {"valor": 249, "palabra": "siempre"}, {"valor": 241, "palabra": "nuestros"}, {"valor": 235, "palabra": "estado"}, {"valor": 210, "palabra": "porque"}, {"valor": 203, "palabra": "programa"}, {"valor": 189, "palabra": "venceremos"}, {"valor": 172, "palabra": "dictador"}, {"valor": 166, "palabra": "cristo"}, {"valor": 162, "palabra": "venezolano"}, {"valor": 160, "palabra": "seguimos"}, {"valor": 147, "palabra": "jajaja"}, {"valor": 145, "palabra": "gracias"}, {"valor": 142, "palabra": "quiere"}, {"valor": 142, "palabra": "cuando"}, {"valor": 142, "palabra": "chávez"}, {"valor": 141, "palabra": "nacional"}, {"valor": 139, "palabra": "municipio"}, {"valor": 136, "palabra": "símbolos"}, {"valor": 135, "palabra": "excelente"}, {"valor": 132, "palabra": "patrios"}, {"valor": 123, "palabra": "venezolanos"}, {"valor": 118, "palabra": "trabajo"}, {"valor": 112, "palabra": "estamos"}, {"valor": 112, "palabra": "sintonía"}, {"valor": 111, "palabra": "contra"}, {"valor": 110, "palabra": "hundiendo"}, {"valor": 103, "palabra": "nicolas"}, {"valor": 103, "palabra": "seguir"}, {"valor": 101, "palabra": "compromiso"}, {"valor": 100, "palabra": "bolívar"}, {"valor": 99, "palabra": "través"}]}, "2024-03-05-2024-03-05": {"VEN - Nicolás Maduro - TW": [{"valor": 1866, "palabra": "presidente"}, {"valor": 1472, "palabra": "maduro"}, {"valor": 1396, "palabra": "venezuela"}, {"valor": 1034, "palabra": "chávez"}, {"valor": 824, "palabra": "nuestro"}, {"valor": 786, "palabra": "pueblo"}, {"valor": 756, "palabra": "nicolás"}, {"valor": 675, "palabra": "comandante"}, {"valor": 452, "palabra": "siempre"}, {"valor": 377, "palabra": "gobierno"}, {"valor": 324, "palabra": "patria"}, {"valor": 296, "palabra": "legado"}, {"valor": 287, "palabra": "siembra"}, {"valor": 259, "palabra": "eterno"}, {"valor": 239, "palabra": "elecciones"}, {"valor": 238, "palabra": "porque"}, {"valor": 236, "palabra": "revolución"}, {"valor": 221, "palabra": "bolivariana"}, {"valor": 211, "palabra": "cuando"}, {"valor": 205, "palabra": "rafael"}, {"valor": 198, "palabra": "dictador"}, {"valor": 197, "palabra": "nuestra"}, {"valor": 196, "palabra": "corazón"}, {"valor": 187, "palabra": "venezolano"}, {"valor": 185, "palabra": "nicolas"}, {"valor": 184, "palabra": "nacional"}, {"valor": 182, "palabra": "corina"}, {"valor": 180, "palabra": "justicia"}, {"valor": 174, "palabra": "social"}, {"valor": 173, "palabra": "partida"}, {"valor": 172, "palabra": "muerte"}, {"valor": 170, "palabra": "tienen"}, {"valor": 163, "palabra": "gracias"}, {"valor": 158, "palabra": "contra"}, {"valor": 156, "palabra": "venceremos"}, {"valor": 152, "palabra": "estado"}, {"valor": 149, "palabra": "nosotros"}, {"valor": 147, "palabra": "municipio"}, {"valor": 146, "palabra": "venezolanos"}, {"valor": 143, "palabra": "dictadura"}]}, "2024-03-06-2024-03-06": {"VEN - Nicolás Maduro - TW": [{"valor": 1432, "palabra": "presidente"}, {"valor": 1359, "palabra": "maduro"}, {"valor": 1130, "palabra": "venezuela"}, {"valor": 808, "palabra": "pueblo"}, {"valor": 704, "palabra": "nicolás"}, {"valor": 609, "palabra": "nuestro"}, {"valor": 419, "palabra": "chávez"}, {"valor": 375, "palabra": "elecciones"}, {"valor": 301, "palabra": "gobierno"}, {"valor": 295, "palabra": "patria"}, {"valor": 274, "palabra": "nuestra"}, {"valor": 268, "palabra": "siempre"}, {"valor": 249, "palabra": "porque"}, {"valor": 220, "palabra": "estado"}, {"valor": 215, "palabra": "venceremos"}, {"valor": 203, "palabra": "comandante"}, {"valor": 202, "palabra": "cuando"}, {"valor": 187, "palabra": "nacional"}, {"valor": 182, "palabra": "venezolano"}, {"valor": 177, "palabra": "justicia"}, {"valor": 177, "palabra": "social"}, {"valor": 173, "palabra": "corina"}, {"valor": 165, "palabra": "municipio"}, {"valor": 163, "palabra": "misión"}, {"valor": 152, "palabra": "tienen"}, {"valor": 150, "palabra": "nosotros"}, {"valor": 149, "palabra": "bienestar"}, {"valor": 146, "palabra": "contra"}, {"valor": 141, "palabra": "venezolanos"}, {"valor": 141, "palabra": "presidenciales"}, {"valor": 140, "palabra": "gracias"}, {"valor": 139, "palabra": "nicolas"}, {"valor": 139, "palabra": "victoria"}, {"valor": 134, "palabra": "ustedes"}, {"valor": 133, "palabra": "igualdad"}, {"valor": 129, "palabra": "dictador"}, {"valor": 122, "palabra": "nuestros"}, {"valor": 122, "palabra": "compromiso"}, {"valor": 119, "palabra": "trabajo"}, {"valor": 118, "palabra": "quiere"}]}, "2024-03-07-2024-03-07": {"VEN - Nicolás Maduro - TW": [{"valor": 1354, "palabra": "presidente"}, {"valor": 1253, "palabra": "maduro"}, {"valor": 931, "palabra": "venezuela"}, {"valor": 772, "palabra": "pueblo"}, {"valor": 667, "palabra": "nicolás"}, {"valor": 546, "palabra": "nuestro"}, {"valor": 291, "palabra": "gobierno"}, {"valor": 284, "palabra": "patria"}, {"valor": 250, "palabra": "nuestra"}, {"valor": 242, "palabra": "porque"}, {"valor": 240, "palabra": "candidato"}, {"valor": 238, "palabra": "cuando"}, {"valor": 236, "palabra": "elecciones"}, {"valor": 218, "palabra": "estado"}, {"valor": 203, "palabra": "siempre"}, {"valor": 184, "palabra": "chávez"}, {"valor": 181, "palabra": "municipio"}, {"valor": 161, "palabra": "nicolas"}, {"valor": 153, "palabra": "corina"}, {"valor": 149, "palabra": "venezolano"}, {"valor": 146, "palabra": "venezolanos"}, {"valor": 144, "palabra": "nuestros"}, {"valor": 144, "palabra": "venceremos"}, {"valor": 140, "palabra": "seguimos"}, {"valor": 139, "palabra": "misión"}, {"valor": 137, "palabra": "nacional"}, {"valor": 134, "palabra": "tienen"}, {"valor": 129, "palabra": "gracias"}, {"valor": 128, "palabra": "estamos"}, {"valor": 128, "palabra": "compromiso"}, {"valor": 116, "palabra": "quiere"}, {"valor": 112, "palabra": "contra"}, {"valor": 111, "palabra": "trabajo"}, {"valor": 111, "palabra": "ustedes"}, {"valor": 106, "palabra": "también"}, {"valor": 104, "palabra": "parroquia"}, {"valor": 103, "palabra": "jajaja"}, {"valor": 101, "palabra": "bienestar"}, {"valor": 99, "palabra": "justicia"}, {"valor": 99, "palabra": "revolución"}]}, "2024-03-08-2024-03-08": {"VEN - Nicolás Maduro - TW": [{"valor": 826, "palabra": "presidente"}, {"valor": 795, "palabra": "maduro"}, {"valor": 525, "palabra": "venezuela"}, {"valor": 508, "palabra": "pueblo"}, {"valor": 386, "palabra": "nicolás"}, {"valor": 312, "palabra": "mujeres"}, {"valor": 298, "palabra": "nuestro"}, {"valor": 198, "palabra": "patria"}, {"valor": 181, "palabra": "nuestra"}, {"valor": 171, "palabra": "porque"}, {"valor": 148, "palabra": "gobierno"}, {"valor": 140, "palabra": "candidato"}, {"valor": 135, "palabra": "chávez"}, {"valor": 120, "palabra": "cuando"}, {"valor": 116, "palabra": "internacional"}, {"valor": 112, "palabra": "siempre"}, {"valor": 109, "palabra": "municipio"}, {"valor": 109, "palabra": "estado"}, {"valor": 108, "palabra": "gracias"}, {"valor": 106, "palabra": "tienen"}, {"valor": 99, "palabra": "jajajaja"}, {"valor": 93, "palabra": "nacional"}, {"valor": 90, "palabra": "elecciones"}, {"valor": 90, "palabra": "nicolas"}, {"valor": 88, "palabra": "venceremos"}, {"valor": 81, "palabra": "corina"}, {"valor": 80, "palabra": "programa"}, {"valor": 73, "palabra": "parroquia"}, {"valor": 71, "palabra": "nuestras"}, {"valor": 68, "palabra": "jajaja"}, {"valor": 67, "palabra": "trabajo"}, {"valor": 66, "palabra": "victoria"}, {"valor": 64, "palabra": "misión"}, {"valor": 64, "palabra": "atención"}, {"valor": 62, "palabra": "venezolano"}, {"valor": 62, "palabra": "ustedes"}, {"valor": 62, "palabra": "revolución"}, {"valor": 57, "palabra": "quiere"}, {"valor": 56, "palabra": "calles"}, {"valor": 55, "palabra": "comunidad"}]}, "2024-03-09-2024-03-09": {"VEN - Nicolás Maduro - TW": [{"valor": 521, "palabra": "presidente"}, {"valor": 465, "palabra": "maduro"}, {"valor": 324, "palabra": "venezuela"}, {"valor": 271, "palabra": "nicolás"}, {"valor": 223, "palabra": "candidato"}, {"valor": 215, "palabra": "pueblo"}, {"valor": 209, "palabra": "nuestro"}, {"valor": 132, "palabra": "elecciones"}, {"valor": 119, "palabra": "municipio"}, {"valor": 101, "palabra": "estado"}, {"valor": 86, "palabra": "patria"}, {"valor": 81, "palabra": "gobierno"}, {"valor": 74, "palabra": "nicolas"}, {"valor": 71, "palabra": "presidenciales"}, {"valor": 71, "palabra": "parroquia"}, {"valor": 71, "palabra": "chávez"}, {"valor": 69, "palabra": "cuando"}, {"valor": 69, "palabra": "asamblea"}, {"valor": 68, "palabra": "porque"}, {"valor": 60, "palabra": "nuestra"}, {"valor": 58, "palabra": "nacional"}, {"valor": 57, "palabra": "gracias"}, {"valor": 53, "palabra": "presidencial"}, {"valor": 53, "palabra": "corina"}, {"valor": 48, "palabra": "postulación"}, {"valor": 45, "palabra": "venezolano"}, {"valor": 45, "palabra": "siempre"}, {"valor": 43, "palabra": "asambleas"}, {"valor": 41, "palabra": "bolívar"}, {"valor": 39, "palabra": "contra"}, {"valor": 39, "palabra": "trabajo"}, {"valor": 38, "palabra": "misión"}, {"valor": 38, "palabra": "venceremos"}, {"valor": 37, "palabra": "mujeres"}, {"valor": 36, "palabra": "machado"}, {"valor": 35, "palabra": "seguir"}, {"valor": 35, "palabra": "revolución"}, {"valor": 34, "palabra": "tienen"}, {"valor": 34, "palabra": "comunidad"}, {"valor": 34, "palabra": "compromiso"}]}, "2024-03-10-2024-03-10": {"VEN - Nicolás Maduro - TW": [{"valor": 1301, "palabra": "pueblo"}, {"valor": 1122, "palabra": "presidente"}, {"valor": 1053, "palabra": "maduro"}, {"valor": 990, "palabra": "venezuela"}, {"valor": 596, "palabra": "nuestro"}, {"valor": 553, "palabra": "nicolás"}, {"valor": 343, "palabra": "siempre"}, {"valor": 339, "palabra": "médico"}, {"valor": 314, "palabra": "nuestra"}, {"valor": 288, "palabra": "patria"}, {"valor": 251, "palabra": "venceremos"}, {"valor": 229, "palabra": "gobierno"}, {"valor": 226, "palabra": "tenemos"}, {"valor": 218, "palabra": "venezolano"}, {"valor": 214, "palabra": "contra"}, {"valor": 206, "palabra": "estado"}, {"valor": 198, "palabra": "vargas"}, {"valor": 197, "palabra": "porque"}, {"valor": 192, "palabra": "candidato"}, {"valor": 172, "palabra": "bolívar"}, {"valor": 170, "palabra": "cuando"}, {"valor": 154, "palabra": "elecciones"}, {"valor": 150, "palabra": "corina"}, {"valor": 150, "palabra": "municipio"}, {"valor": 149, "palabra": "nombre"}, {"valor": 139, "palabra": "espera"}, {"valor": 136, "palabra": "seguimos"}, {"valor": 134, "palabra": "bienestar"}, {"valor": 134, "palabra": "cárcel"}, {"valor": 132, "palabra": "bastante"}, {"valor": 130, "palabra": "misión"}, {"valor": 126, "palabra": "chávez"}, {"valor": 126, "palabra": "pisoteado"}, {"valor": 125, "palabra": "trabajando"}, {"valor": 125, "palabra": "botado"}, {"valor": 125, "palabra": "agradecerte"}, {"valor": 125, "palabra": "ensucies"}, {"valor": 124, "palabra": "estamos"}, {"valor": 123, "palabra": "gracias"}, {"valor": 122, "palabra": "servicio"}]}, "2024-03-11-2024-03-11": {"VEN - Nicolás Maduro - TW": [{"valor": 1365, "palabra": "maduro"}, {"valor": 1340, "palabra": "presidente"}, {"valor": 1220, "palabra": "nuestro"}, {"valor": 876, "palabra": "venezuela"}, {"valor": 772, "palabra": "pueblo"}, {"valor": 648, "palabra": "nuestra"}, {"valor": 647, "palabra": "nicolás"}, {"valor": 499, "palabra": "patria"}, {"valor": 432, "palabra": "ambiente"}, {"valor": 414, "palabra": "programa"}, {"valor": 397, "palabra": "siempre"}, {"valor": 387, "palabra": "venceremos"}, {"valor": 367, "palabra": "nuestros"}, {"valor": 350, "palabra": "ilegal"}, {"valor": 339, "palabra": "candidato"}, {"valor": 337, "palabra": "minería"}, {"valor": 336, "palabra": "seguimos"}, {"valor": 336, "palabra": "estado"}, {"valor": 307, "palabra": "parques"}, {"valor": 300, "palabra": "protección"}, {"valor": 249, "palabra": "nacional"}, {"valor": 225, "palabra": "gobierno"}, {"valor": 225, "palabra": "porque"}, {"valor": 218, "palabra": "territorio"}, {"valor": 217, "palabra": "contra"}, {"valor": 208, "palabra": "elecciones"}, {"valor": 208, "palabra": "nacionales"}, {"valor": 200, "palabra": "cumpliendo"}, {"valor": 199, "palabra": "venezolano"}, {"valor": 186, "palabra": "bienestar"}, {"valor": 185, "palabra": "cuando"}, {"valor": 184, "palabra": "naturales"}, {"valor": 182, "palabra": "compromiso"}, {"valor": 182, "palabra": "naturaleza"}, {"valor": 181, "palabra": "venezolanos"}, {"valor": 177, "palabra": "comandante"}, {"valor": 172, "palabra": "sintonía"}, {"valor": 160, "palabra": "municipio"}, {"valor": 160, "palabra": "lealtad"}, {"valor": 153, "palabra": "victoria"}]}}